LICENCE
README.md
setup.cfg
setup.py
datatable_ajax_request_parser/__init__.py
datatable_ajax_request_parser/dataclasses.py
datatable_ajax_request_parser/django_extension.py
datatable_ajax_request_parser/parser.py
datatable_ajax_request_parser/test_django_extension.py
datatable_ajax_request_parser/test_parser.py
datatable_ajax_request_parser/utils.py
datatable_ajax_request_parser.egg-info/PKG-INFO
datatable_ajax_request_parser.egg-info/SOURCES.txt
datatable_ajax_request_parser.egg-info/dependency_links.txt
datatable_ajax_request_parser.egg-info/requires.txt
datatable_ajax_request_parser.egg-info/top_level.txt