Metadata-Version: 2.1
Name: datatable-ajax-request-parser
Version: 1.0.0
Summary: Helper function to parse ajax datatable request into usable dictionary
Author: Yap ZhiHon
Author-email: y.zhihon@gmail.com
Classifier: Operating System :: OS Independent
Requires-Python: >=3.10
Provides-Extra: Django
License-File: LICENCE
